bordr/__init__.py
bordr/InitialTagger/InitialTagger4Bo.py
bordr/InitialTagger/__init__.py
bordr/SCRDRlearner/Node.py
bordr/SCRDRlearner/Object.py
bordr/SCRDRlearner/SCRDRTree.py
bordr/SCRDRlearner/SCRDRTreeLearner.py
bordr/SCRDRlearner/__init__.py
bordr/Utility/Config.py
bordr/Utility/Eval.py
bordr/Utility/LexiconCreator.py
bordr/Utility/Utils.py
bordr/Utility/__init__.py
bordr/pSCRDRtagger/RDRPOSTagger.py
bordr/pSCRDRtagger/__init__.py
bordr-0.1.4.dist-info/METADATA
bordr-0.1.4.dist-info/WHEEL
bordr-0.1.4.dist-info/top_level.txt
bordr-0.1.4.dist-info/RECORD
