Metadata-Version: 2.1
Name: bordr
Version: 0.1.4
Summary: A  fast and accurate POS and morphological tagging toolkit, lightly adapted to Tibetan language.
Home-page: https://github.com/Esukhia/RDRPOSTagger
Author: Dat Quoc Nguyen
Author-email: dqnguyen@unimelb.edu.au
License: GNU General Public License
Project-URL: Source, https://github.com/Esukhia/RDRPOSTagger
Project-URL: Tracker, https://github.com/Esukhia/RDRPOSTagger/issues
Keywords: part-of-speech-tagger java nlp pos-tagging pos-tagger python3
Platform: UNKNOWN
Classifier: Development Status :: 3 - Alpha
Classifier: Topic :: Text Processing :: Linguistic
Classifier: Programming Language :: Python :: 3
Classifier: Operating System :: OS Independent
Classifier: Intended Audience :: Developers
Classifier: Intended Audience :: Science/Research
Classifier: License :: OSI Approved :: GNU General Public License (GPL)
Classifier: Natural Language :: Tibetan
Requires-Python: >=3.6
